scikit-ribo/__init__.py
scikit-ribo/asite_predict.py
scikit-ribo/bam_process.py
scikit-ribo/call_rnafold.py
scikit-ribo/gtf_preprocess.py
scikit-ribo/merge_df.py
scikit-ribo/model_te.py
scikit-ribo/plot_ribo.py
scikit-ribo/process_rnafold.py
scikit-ribo/scikit-ribo-build.py
scikit-ribo/scikit-ribo-run.py
scikit-ribo/scikit-ribo.py
scikit_ribo/__init__.py
scikit_ribo/asite_predict.py
scikit_ribo/bam_process.py
scikit_ribo/call_rnafold.py
scikit_ribo/gtf_preprocess.py
scikit_ribo/merge_df.py
scikit_ribo/model_te.py
scikit_ribo/plot_ribo.py
scikit_ribo/process_rnafold.py
scikit_ribo/scikit-ribo-build.py
scikit_ribo/scikit-ribo-run.py
scikit_ribo-0.2.4b1.data/scripts/plot_ribo.py
scikit_ribo-0.2.4b1.data/scripts/scikit-ribo-build.py
scikit_ribo-0.2.4b1.data/scripts/scikit-ribo-run.py
scikit_ribo-0.2.4b1.data/scripts/scikit-ribo.py
scikit_ribo-0.2.4b1.dist-info/DESCRIPTION.rst
scikit_ribo-0.2.4b1.dist-info/METADATA
scikit_ribo-0.2.4b1.dist-info/RECORD
scikit_ribo-0.2.4b1.dist-info/WHEEL
scikit_ribo-0.2.4b1.dist-info/metadata.json
scikit_ribo-0.2.4b1.dist-info/top_level.txt
