Metadata-Version: 2.0
Name: scikit-ribo
Version: 0.2.4b1
Summary: A scikit framework for joint analysis of Riboseq and RNAseq data
Home-page: https://github.com/hanfang/scikit-ribo
Author: Han Fang
Author-email: hanfang.cshl@gmail.com
License: GPLv2
Keywords: bioinformatics genomics glm glmnet ridge riboseq
Platform: UNKNOWN
Classifier: Development Status :: 4 - Beta
Classifier: Intended Audience :: Science/Research
Classifier: Topic :: Scientific/Engineering :: Bio-Informatics
Classifier: License :: OSI Approved :: GNU General Public License v2 (GPLv2)
Classifier: Programming Language :: Python :: 3
Classifier: Programming Language :: Python :: 3.4
Classifier: Operating System :: Unix
Requires-Dist: colorama (>=0.3.7)
Requires-Dist: gffutils (>=0.8.7.1)
Requires-Dist: glmnet-py (>=0.1.0b2)
Requires-Dist: joblib (>=0.10.3)
Requires-Dist: matplotlib (>=1.5.1)
Requires-Dist: numpy (>=1.11.2)
Requires-Dist: pandas (>=0.19.2)
Requires-Dist: pybedtools (>=0.7.8)
Requires-Dist: pyfiglet (>=0.7.5)
Requires-Dist: pysam (>=0.9.1.4)
Requires-Dist: scikit-learn (>=0.18)
Requires-Dist: scipy (>=0.18.1)
Requires-Dist: seaborn (>=0.7.0)
Requires-Dist: termcolor (>=1.1.0)
